AUTHORS
MANIFEST.in
README.rst
setup.py
chevah/__init__.py
chevah/__init__.pyc
chevah/buildbot_configuration_builder/__init__.py
chevah/buildbot_configuration_builder/__init__.pyc
chevah/buildbot_configuration_builder/builder.py
chevah/buildbot_configuration_builder/builder.pyc
chevah_buildbot_configuration_builder.egg-info/PKG-INFO
chevah_buildbot_configuration_builder.egg-info/SOURCES.txt
chevah_buildbot_configuration_builder.egg-info/dependency_links.txt
chevah_buildbot_configuration_builder.egg-info/namespace_packages.txt
chevah_buildbot_configuration_builder.egg-info/requires.txt
chevah_buildbot_configuration_builder.egg-info/top_level.txt