Metadata-Version: 1.1
Name: chevah-buildbot-configuration-builder
Version: 0.1.0
Summary: Configuration layer on top of Buildbot dict.
Home-page: https://github.com/chevah/buildbot-configuration-builder
Author: Adi Roiban
Author-email: adi.roiban@chevah.com
License: MIT
Platform: any
Classifier: Development Status :: 4 - Beta
Classifier: Intended Audience :: Developers
Classifier: Programming Language :: Python
